[
    {
        "klasifikasi": "TUN",
        "total": 53101
    },
    {
        "klasifikasi": "PAJAK",
        "total": 19793
    },
    {
        "klasifikasi": "PERTANAHAN",
        "total": 11958
    },
    {
        "klasifikasi": "KEPEGAWAIAN",
        "total": 5910
    },
    {
        "klasifikasi": "LAIN LAIN TERMASUK PIUTANG",
        "total": 4151
    },
    {
        "klasifikasi": "PERIJINAN",
        "total": 2280
    },
    {
        "klasifikasi": "HAK UJI MATERIIL",
        "total": 807
    },
    {
        "klasifikasi": "PILKADA",
        "total": 762
    },
    {
        "klasifikasi": "LELANG",
        "total": 503
    },
    {
        "klasifikasi": "KIP",
        "total": 312
    },
    {
        "klasifikasi": "TENDER",
        "total": 305
    },
    {
        "klasifikasi": "BADAN HUKUM",
        "total": 281
    },
    {
        "klasifikasi": "PARTAI POLITIK",
        "total": 169
    },
    {
        "klasifikasi": "PERUMAHAN",
        "total": 103
    },
    {
        "klasifikasi": "PENDIDIKAN",
        "total": 92
    },
    {
        "klasifikasi": "KEPENDUDUKAN KEWARGANEGARAAN",
        "total": 42
    },
    {
        "klasifikasi": "PELANGGARAN ADMINISTRASI PEMILIHAN",
        "total": 12
    },
    {
        "klasifikasi": "ASURANSI",
        "total": 7
    }
]